{"header": "{\"msgid\": \"15041\", \"msgtype\": \"PATCH-DOC\"}", "metadata": "{}", "content": "{\"events\": [{\"attr\": \"children\", \"kind\": \"ModelChanged\", \"model\": {\"id\": \"10989\"}, \"new\": [{\"id\": \"14967\"}]}, {\"attr\": \"y_range\", \"kind\": \"ModelChanged\", \"model\": {\"id\": \"14967\"}, \"new\": {\"id\": \"14964\"}}], \"references\": [{\"attributes\": {\"fill_alpha\": {\"value\": 0.1}, \"fill_color\": {\"value\": \"#0f0f0f\"}, \"line_alpha\": {\"value\": 0.1}, \"line_color\": {\"value\": \"#0f0f0f\"}, \"size\": {\"units\": \"screen\", \"value\": 5.477225575051661}, \"x\": {\"field\": \"cyl\"}, \"y\": {\"field\": \"cyl\"}}, \"id\": \"15001\", \"type\": \"Scatter\"}, {\"attributes\": {}, \"id\": \"14977\", \"type\": \"BasicTicker\"}, {\"attributes\": {\"active_drag\": \"auto\", \"active_inspect\": \"auto\", \"active_multi\": null, \"active_scroll\": \"auto\", \"active_tap\": \"auto\", \"tools\": [{\"id\": \"14966\"}, {\"id\": \"14984\"}, {\"id\": \"14985\"}, {\"id\": \"14986\"}, {\"id\": \"14987\"}, {\"id\": \"14988\"}]}, \"id\": \"14990\", \"type\": \"Toolbar\"}, {\"attributes\": {\"align\": null, \"below\": [{\"id\": \"14976\"}], \"center\": [{\"id\": \"14979\"}, {\"id\": \"14983\"}], \"left\": [{\"id\": \"14980\"}], \"margin\": null, \"min_border_bottom\": 10, \"min_border_left\": 10, \"min_border_right\": 10, \"min_border_top\": 10, \"plot_height\": 300, \"plot_width\": 700, \"renderers\": [{\"id\": \"15003\"}], \"sizing_mode\": \"fixed\", \"title\": {\"id\": \"14968\"}, \"toolbar\": {\"id\": \"14990\"}, \"x_range\": {\"id\": \"14964\"}, \"x_scale\": {\"id\": \"14972\"}, \"y_range\": {\"id\": \"14964\"}, \"y_scale\": {\"id\": \"14974\"}}, \"id\": \"14967\", \"subtype\": \"Figure\", \"type\": \"Plot\"}, {\"attributes\": {\"fill_alpha\": {\"value\": 0.2}, \"fill_color\": {\"value\": \"#0f0f0f\"}, \"line_alpha\": {\"value\": 0.2}, \"line_color\": {\"value\": \"#0f0f0f\"}, \"size\": {\"units\": \"screen\", \"value\": 5.477225575051661}, \"x\": {\"field\": \"cyl\"}, \"y\": {\"field\": \"cyl\"}}, \"id\": \"15002\", \"type\": \"Scatter\"}, {\"attributes\": {\"data\": {\"cyl\": [8, 8, 8, 8, 8, 8, 8, 8, 8, 8, 8, 8, 8, 8, 4, 6, 6, 6, 4, 4, 4, 4, 4, 4, 6, 8, 8, 8, 8, 4, 4, 4, 6, 6, 6, 6, 6, 8, 8, 8, 8, 8, 8, 8, 6, 4, 6, 6, 4, 4, 4, 4, 4, 4, 4, 4, 4, 4, 4, 4, 4, 8, 8, 8, 8, 8, 8, 8, 8, 8, 3, 8, 8, 8, 8, 4, 4, 4, 4, 4, 4, 4, 4, 4, 8, 8, 8, 8, 8, 8, 8, 8, 8, 8, 8, 8, 6, 6, 6, 6, 6, 4, 8, 8, 8, 8, 6, 4, 4, 4, 3, 4, 6, 4, 8, 8, 4, 4, 4, 4, 8, 4, 6, 8, 6, 6, 6, 4, 4, 4, 4, 6, 6, 6, 8, 8, 8, 8, 8, 4, 4, 4, 4, 4, 4, 4, 4, 4, 4, 4, 6, 6, 6, 6, 8, 8, 8, 8, 6, 6, 6, 6, 6, 8, 8, 4, 4, 6, 4, 4, 4, 4, 6, 4, 6, 4, 4, 4, 4, 4, 4, 4, 4, 4, 4, 8, 8, 8, 8, 6, 6, 6, 6, 4, 4, 4, 4, 6, 6, 6, 6, 4, 4, 4, 4, 4, 8, 4, 6, 6, 8, 8, 8, 8, 4, 4, 4, 4, 4, 8, 8, 8, 8, 6, 6, 6, 6, 8, 8, 8, 8, 4, 4, 4, 4, 4, 4, 4, 4, 6, 4, 3, 4, 4, 4, 4, 4, 8, 8, 8, 6, 6, 6, 4, 6, 6, 6, 6, 6, 6, 8, 6, 8, 8, 4, 4, 4, 4, 4, 4, 4, 4, 5, 6, 4, 6, 4, 4, 6, 6, 4, 6, 6, 8, 8, 8, 8, 8, 8, 8, 8, 4, 4, 4, 4, 5, 8, 4, 8, 4, 4, 4, 4, 4, 6, 6, 4, 4, 4, 4, 4, 4, 4, 4, 6, 4, 4, 4, 4, 4, 4, 4, 4, 4, 4, 5, 4, 4, 4, 4, 6, 3, 4, 4, 4, 4, 4, 6, 4, 4, 4, 4, 4, 4, 4, 4, 4, 4, 4, 4, 4, 4, 4, 4, 4, 6, 6, 6, 6, 8, 6, 6, 4, 4, 4, 4, 4, 4, 4, 4, 4, 4, 4, 4, 4, 4, 4, 4, 4, 4, 6, 6, 4, 6, 4, 4, 4, 4, 4, 4, 4, 4]}, \"selected\": {\"id\": \"14998\"}, \"selection_policy\": {\"id\": \"15016\"}}, \"id\": \"14997\", \"type\": \"ColumnDataSource\"}, {\"attributes\": {\"axis\": {\"id\": \"14980\"}, \"dimension\": 1, \"grid_line_color\": null, \"ticker\": null}, \"id\": \"14983\", \"type\": \"Grid\"}, {\"attributes\": {\"axis_label\": \"cyl\", \"bounds\": \"auto\", \"formatter\": {\"id\": \"15005\"}, \"major_label_orientation\": \"horizontal\", \"ticker\": {\"id\": \"14977\"}}, \"id\": \"14976\", \"type\": \"LinearAxis\"}, {\"attributes\": {\"fill_color\": {\"value\": \"#0f0f0f\"}, \"line_color\": {\"value\": \"#0f0f0f\"}, \"size\": {\"units\": \"screen\", \"value\": 5.477225575051661}, \"x\": {\"field\": \"cyl\"}, \"y\": {\"field\": \"cyl\"}}, \"id\": \"15000\", \"type\": \"Scatter\"}, {\"attributes\": {\"end\": 8.214285714285714, \"reset_end\": 8.214285714285714, \"reset_start\": 2.7857142857142856, \"start\": 2.7857142857142856, \"tags\": [[[\"cyl\", \"cyl\", null]]]}, \"id\": \"14964\", \"type\": \"Range1d\"}, {\"attributes\": {}, \"id\": \"14988\", \"type\": \"ResetTool\"}, {\"attributes\": {\"axis\": {\"id\": \"14976\"}, \"grid_line_color\": null, \"ticker\": null}, \"id\": \"14979\", \"type\": \"Grid\"}, {\"attributes\": {}, \"id\": \"14998\", \"type\": \"Selection\"}, {\"attributes\": {}, \"id\": \"15005\", \"type\": \"BasicTickFormatter\"}, {\"attributes\": {}, \"id\": \"14974\", \"type\": \"LinearScale\"}, {\"attributes\": {\"overlay\": {\"id\": \"14989\"}}, \"id\": \"14987\", \"type\": \"BoxZoomTool\"}, {\"attributes\": {\"callback\": null, \"renderers\": [{\"id\": \"15003\"}], \"tags\": [\"hv_created\"], \"tooltips\": [[\"cyl\", \"@{cyl}\"]]}, \"id\": \"14966\", \"type\": \"HoverTool\"}, {\"attributes\": {\"source\": {\"id\": \"14997\"}}, \"id\": \"15004\", \"type\": \"CDSView\"}, {\"attributes\": {}, \"id\": \"14972\", \"type\": \"LinearScale\"}, {\"attributes\": {}, \"id\": \"15016\", \"type\": \"UnionRenderers\"}, {\"attributes\": {}, \"id\": \"14985\", \"type\": \"PanTool\"}, {\"attributes\": {}, \"id\": \"14981\", \"type\": \"BasicTicker\"}, {\"attributes\": {}, \"id\": \"15007\", \"type\": \"BasicTickFormatter\"}, {\"attributes\": {}, \"id\": \"14984\", \"type\": \"SaveTool\"}, {\"attributes\": {\"text\": \"\", \"text_color\": {\"value\": \"black\"}, \"text_font_size\": {\"value\": \"12pt\"}}, \"id\": \"14968\", \"type\": \"Title\"}, {\"attributes\": {\"bottom_units\": \"screen\", \"fill_alpha\": 0.5, \"fill_color\": \"lightgrey\", \"left_units\": \"screen\", \"level\": \"overlay\", \"line_alpha\": 1.0, \"line_color\": \"black\", \"line_dash\": [4, 4], \"line_width\": 2, \"render_mode\": \"css\", \"right_units\": \"screen\", \"top_units\": \"screen\"}, \"id\": \"14989\", \"type\": \"BoxAnnotation\"}, {\"attributes\": {\"data_source\": {\"id\": \"14997\"}, \"glyph\": {\"id\": \"15000\"}, \"hover_glyph\": null, \"muted_glyph\": {\"id\": \"15002\"}, \"nonselection_glyph\": {\"id\": \"15001\"}, \"selection_glyph\": null, \"view\": {\"id\": \"15004\"}}, \"id\": \"15003\", \"type\": \"GlyphRenderer\"}, {\"attributes\": {}, \"id\": \"14986\", \"type\": \"WheelZoomTool\"}, {\"attributes\": {\"axis_label\": \"cyl\", \"bounds\": \"auto\", \"formatter\": {\"id\": \"15007\"}, \"major_label_orientation\": \"horizontal\", \"ticker\": {\"id\": \"14981\"}}, \"id\": \"14980\", \"type\": \"LinearAxis\"}]}"}